JixianVerificationCodeEmail/__init__.py
JixianVerificationCodeEmail/main.py
JixianVerificationCodeEmail-1.0.dist-info/METADATA
JixianVerificationCodeEmail-1.0.dist-info/WHEEL
JixianVerificationCodeEmail-1.0.dist-info/top_level.txt
JixianVerificationCodeEmail-1.0.dist-info/RECORD
