Metadata-Version: 2.1
Name: JixianVerificationCodeEmail
Version: 1.0
Summary: 即现验证码邮箱版
Home-page: https://www.jixiannet.com
Author: Moxin
Author-email: lqn@jixiannet.com
